{
  "best_global_step": null,
  "best_metric": null,
  "best_model_checkpoint": null,
  "epoch": 0.2992727671757629,
  "eval_steps": 20000,
  "global_step": 180000,
  "is_hyper_param_search": false,
  "is_local_process_zero": true,
  "is_world_process_zero": true,
  "log_history": [
    {
      "epoch": 0.03325252968619588,
      "grad_norm": 1.992497205734253,
      "learning_rate": 5.320138729553851e-05,
      "loss": 1.8697,
      "step": 20000
    },
    {
      "epoch": 0.03325252968619588,
      "eval_loss": 1.7746458053588867,
      "eval_runtime": 1286.2102,
      "eval_samples_per_second": 71.289,
      "eval_steps_per_second": 8.911,
      "step": 20000
    },
    {
      "epoch": 0.06650505937239176,
      "grad_norm": 0.7733168005943298,
      "learning_rate": 0.0001064054347934519,
      "loss": 1.6614,
      "step": 40000
    },
    {
      "epoch": 0.06650505937239176,
      "eval_loss": 1.6638431549072266,
      "eval_runtime": 1286.8945,
      "eval_samples_per_second": 71.251,
      "eval_steps_per_second": 8.907,
      "step": 40000
    },
    {
      "epoch": 0.09975758905858763,
      "grad_norm": 0.7508602142333984,
      "learning_rate": 0.00015960948229136533,
      "loss": 1.5897,
      "step": 60000
    },
    {
      "epoch": 0.09975758905858763,
      "eval_loss": 1.594363808631897,
      "eval_runtime": 1291.0627,
      "eval_samples_per_second": 71.021,
      "eval_steps_per_second": 8.878,
      "step": 60000
    },
    {
      "epoch": 0.13301011874478352,
      "grad_norm": 0.6895467042922974,
      "learning_rate": 0.00021281352978927873,
      "loss": 1.5384,
      "step": 80000
    },
    {
      "epoch": 0.13301011874478352,
      "eval_loss": 1.5424023866653442,
      "eval_runtime": 1294.2873,
      "eval_samples_per_second": 70.844,
      "eval_steps_per_second": 8.856,
      "step": 80000
    },
    {
      "epoch": 0.16626264843097938,
      "grad_norm": 0.9446073770523071,
      "learning_rate": 0.00026601757728719213,
      "loss": 1.4998,
      "step": 100000
    },
    {
      "epoch": 0.16626264843097938,
      "eval_loss": 1.5064915418624878,
      "eval_runtime": 1286.4209,
      "eval_samples_per_second": 71.278,
      "eval_steps_per_second": 8.91,
      "step": 100000
    },
    {
      "epoch": 0.19951517811717526,
      "grad_norm": 0.7902131676673889,
      "learning_rate": 0.00031922162478510555,
      "loss": 1.4699,
      "step": 120000
    },
    {
      "epoch": 0.19951517811717526,
      "eval_loss": 1.4747350215911865,
      "eval_runtime": 1285.2529,
      "eval_samples_per_second": 71.342,
      "eval_steps_per_second": 8.918,
      "step": 120000
    },
    {
      "epoch": 0.23276770780337114,
      "grad_norm": 0.4308467209339142,
      "learning_rate": 0.000372425672283019,
      "loss": 1.4461,
      "step": 140000
    },
    {
      "epoch": 0.23276770780337114,
      "eval_loss": 1.4554641246795654,
      "eval_runtime": 1289.4013,
      "eval_samples_per_second": 71.113,
      "eval_steps_per_second": 8.889,
      "step": 140000
    },
    {
      "epoch": 0.26602023748956705,
      "grad_norm": 0.5334970355033875,
      "learning_rate": 0.00042562971978093235,
      "loss": 1.4245,
      "step": 160000
    },
    {
      "epoch": 0.26602023748956705,
      "eval_loss": 1.4301685094833374,
      "eval_runtime": 1289.8037,
      "eval_samples_per_second": 71.091,
      "eval_steps_per_second": 8.887,
      "step": 160000
    },
    {
      "epoch": 0.2992727671757629,
      "grad_norm": 0.33289793133735657,
      "learning_rate": 0.0004788337672788457,
      "loss": 1.4077,
      "step": 180000
    },
    {
      "epoch": 0.2992727671757629,
      "eval_loss": 1.4126707315444946,
      "eval_runtime": 1292.1841,
      "eval_samples_per_second": 70.96,
      "eval_steps_per_second": 8.87,
      "step": 180000
    }
  ],
  "logging_steps": 20000,
  "max_steps": 6014580,
  "num_input_tokens_seen": 0,
  "num_train_epochs": 10,
  "save_steps": 20000,
  "stateful_callbacks": {
    "TrainerControl": {
      "args": {
        "should_epoch_stop": false,
        "should_evaluate": false,
        "should_log": false,
        "should_save": true,
        "should_training_stop": false
      },
      "attributes": {}
    }
  },
  "total_flos": 0.0,
  "train_batch_size": 32,
  "trial_name": null,
  "trial_params": null
}
