{
  "best_global_step": null,
  "best_metric": null,
  "best_model_checkpoint": null,
  "epoch": 3.2920004389333917,
  "eval_steps": 20000,
  "global_step": 1980000,
  "is_hyper_param_search": false,
  "is_local_process_zero": true,
  "is_world_process_zero": true,
  "log_history": [
    {
      "epoch": 0.03325252968619588,
      "grad_norm": 1.5333812236785889,
      "learning_rate": 5.320138729553851e-05,
      "loss": 1.9396,
      "step": 20000
    },
    {
      "epoch": 0.03325252968619588,
      "eval_loss": 1.8424595594406128,
      "eval_runtime": 372.5539,
      "eval_samples_per_second": 246.12,
      "eval_steps_per_second": 30.766,
      "step": 20000
    },
    {
      "epoch": 0.06650505937239176,
      "grad_norm": 0.8751625418663025,
      "learning_rate": 0.0001064054347934519,
      "loss": 1.7206,
      "step": 40000
    },
    {
      "epoch": 0.06650505937239176,
      "eval_loss": 1.7306314706802368,
      "eval_runtime": 387.3196,
      "eval_samples_per_second": 236.737,
      "eval_steps_per_second": 29.593,
      "step": 40000
    },
    {
      "epoch": 0.09975758905858763,
      "grad_norm": 0.6199726462364197,
      "learning_rate": 0.00015960948229136533,
      "loss": 1.6521,
      "step": 60000
    },
    {
      "epoch": 0.09975758905858763,
      "eval_loss": 1.6743897199630737,
      "eval_runtime": 387.5556,
      "eval_samples_per_second": 236.593,
      "eval_steps_per_second": 29.575,
      "step": 60000
    },
    {
      "epoch": 0.13301011874478352,
      "grad_norm": 0.7013611197471619,
      "learning_rate": 0.00021281352978927873,
      "loss": 1.6103,
      "step": 80000
    },
    {
      "epoch": 0.13301011874478352,
      "eval_loss": 1.6276719570159912,
      "eval_runtime": 386.0352,
      "eval_samples_per_second": 237.525,
      "eval_steps_per_second": 29.692,
      "step": 80000
    },
    {
      "epoch": 0.16626264843097938,
      "grad_norm": 0.7597078084945679,
      "learning_rate": 0.00026601757728719213,
      "loss": 1.576,
      "step": 100000
    },
    {
      "epoch": 0.16626264843097938,
      "eval_loss": 1.5950343608856201,
      "eval_runtime": 388.3078,
      "eval_samples_per_second": 236.135,
      "eval_steps_per_second": 29.518,
      "step": 100000
    },
    {
      "epoch": 0.19951517811717526,
      "grad_norm": 0.7428387999534607,
      "learning_rate": 0.00031922162478510555,
      "loss": 1.5484,
      "step": 120000
    },
    {
      "epoch": 0.19951517811717526,
      "eval_loss": 1.5650899410247803,
      "eval_runtime": 387.1147,
      "eval_samples_per_second": 236.863,
      "eval_steps_per_second": 29.609,
      "step": 120000
    },
    {
      "epoch": 0.23276770780337114,
      "grad_norm": 0.4061862826347351,
      "learning_rate": 0.000372425672283019,
      "loss": 1.5274,
      "step": 140000
    },
    {
      "epoch": 0.23276770780337114,
      "eval_loss": 1.542771577835083,
      "eval_runtime": 389.373,
      "eval_samples_per_second": 235.489,
      "eval_steps_per_second": 29.437,
      "step": 140000
    },
    {
      "epoch": 0.26602023748956705,
      "grad_norm": 0.382902592420578,
      "learning_rate": 0.00042562971978093235,
      "loss": 1.5083,
      "step": 160000
    },
    {
      "epoch": 0.26602023748956705,
      "eval_loss": 1.5264997482299805,
      "eval_runtime": 377.3056,
      "eval_samples_per_second": 243.021,
      "eval_steps_per_second": 30.379,
      "step": 160000
    },
    {
      "epoch": 0.2992727671757629,
      "grad_norm": 0.2852524518966675,
      "learning_rate": 0.0004788337672788457,
      "loss": 1.4935,
      "step": 180000
    },
    {
      "epoch": 0.2992727671757629,
      "eval_loss": 1.5114439725875854,
      "eval_runtime": 388.803,
      "eval_samples_per_second": 235.834,
      "eval_steps_per_second": 29.48,
      "step": 180000
    },
    {
      "epoch": 0.33252529686195875,
      "grad_norm": 0.2425374686717987,
      "learning_rate": 0.0005320378147767592,
      "loss": 1.4794,
      "step": 200000
    },
    {
      "epoch": 0.33252529686195875,
      "eval_loss": 1.4973304271697998,
      "eval_runtime": 373.4908,
      "eval_samples_per_second": 245.503,
      "eval_steps_per_second": 30.689,
      "step": 200000
    },
    {
      "epoch": 0.36577782654815466,
      "grad_norm": 0.32452335953712463,
      "learning_rate": 0.0005852418622746726,
      "loss": 1.468,
      "step": 220000
    },
    {
      "epoch": 0.36577782654815466,
      "eval_loss": 1.484175443649292,
      "eval_runtime": 373.1964,
      "eval_samples_per_second": 245.696,
      "eval_steps_per_second": 30.713,
      "step": 220000
    },
    {
      "epoch": 0.3990303562343505,
      "grad_norm": 0.4906960129737854,
      "learning_rate": 0.0006384459097725859,
      "loss": 1.4562,
      "step": 240000
    },
    {
      "epoch": 0.3990303562343505,
      "eval_loss": 1.4712624549865723,
      "eval_runtime": 372.3003,
      "eval_samples_per_second": 246.288,
      "eval_steps_per_second": 30.787,
      "step": 240000
    },
    {
      "epoch": 0.4322828859205464,
      "grad_norm": 0.2237827032804489,
      "learning_rate": 0.0006916499572704994,
      "loss": 1.448,
      "step": 260000
    },
    {
      "epoch": 0.4322828859205464,
      "eval_loss": 1.4623297452926636,
      "eval_runtime": 368.2192,
      "eval_samples_per_second": 249.017,
      "eval_steps_per_second": 31.128,
      "step": 260000
    },
    {
      "epoch": 0.4655354156067423,
      "grad_norm": 0.2758028209209442,
      "learning_rate": 0.0007448540047684128,
      "loss": 1.4397,
      "step": 280000
    },
    {
      "epoch": 0.4655354156067423,
      "eval_loss": 1.4529387950897217,
      "eval_runtime": 372.443,
      "eval_samples_per_second": 246.193,
      "eval_steps_per_second": 30.775,
      "step": 280000
    },
    {
      "epoch": 0.4987879452929382,
      "grad_norm": 0.3820866048336029,
      "learning_rate": 0.0007980580522663262,
      "loss": 1.4319,
      "step": 300000
    },
    {
      "epoch": 0.4987879452929382,
      "eval_loss": 1.4468227624893188,
      "eval_runtime": 372.2298,
      "eval_samples_per_second": 246.334,
      "eval_steps_per_second": 30.793,
      "step": 300000
    },
    {
      "epoch": 0.5320404749791341,
      "grad_norm": 0.2278909981250763,
      "learning_rate": 0.0007973019947492506,
      "loss": 1.4234,
      "step": 320000
    },
    {
      "epoch": 0.5320404749791341,
      "eval_loss": 1.4294236898422241,
      "eval_runtime": 368.5436,
      "eval_samples_per_second": 248.798,
      "eval_steps_per_second": 31.101,
      "step": 320000
    },
    {
      "epoch": 0.56529300466533,
      "grad_norm": 0.3006814420223236,
      "learning_rate": 0.0007945017817230447,
      "loss": 1.4138,
      "step": 340000
    },
    {
      "epoch": 0.56529300466533,
      "eval_loss": 1.4227170944213867,
      "eval_runtime": 377.7808,
      "eval_samples_per_second": 242.715,
      "eval_steps_per_second": 30.34,
      "step": 340000
    },
    {
      "epoch": 0.5985455343515258,
      "grad_norm": 0.4820419251918793,
      "learning_rate": 0.0007917015686968387,
      "loss": 1.4052,
      "step": 360000
    },
    {
      "epoch": 0.5985455343515258,
      "eval_loss": 1.4150245189666748,
      "eval_runtime": 372.2586,
      "eval_samples_per_second": 246.315,
      "eval_steps_per_second": 30.79,
      "step": 360000
    },
    {
      "epoch": 0.6317980640377217,
      "grad_norm": 0.36803361773490906,
      "learning_rate": 0.0007889013556706326,
      "loss": 1.3971,
      "step": 380000
    },
    {
      "epoch": 0.6317980640377217,
      "eval_loss": 1.4044901132583618,
      "eval_runtime": 375.1702,
      "eval_samples_per_second": 244.404,
      "eval_steps_per_second": 30.551,
      "step": 380000
    },
    {
      "epoch": 0.6650505937239175,
      "grad_norm": 0.6230485439300537,
      "learning_rate": 0.0007861011426444267,
      "loss": 1.39,
      "step": 400000
    },
    {
      "epoch": 0.6650505937239175,
      "eval_loss": 1.400244951248169,
      "eval_runtime": 375.92,
      "eval_samples_per_second": 243.916,
      "eval_steps_per_second": 30.491,
      "step": 400000
    },
    {
      "epoch": 0.6983031234101135,
      "grad_norm": 0.3081762492656708,
      "learning_rate": 0.0007833009296182207,
      "loss": 1.3839,
      "step": 420000
    },
    {
      "epoch": 0.6983031234101135,
      "eval_loss": 1.3914172649383545,
      "eval_runtime": 363.5412,
      "eval_samples_per_second": 252.222,
      "eval_steps_per_second": 31.529,
      "step": 420000
    },
    {
      "epoch": 0.7315556530963093,
      "grad_norm": 0.34292691946029663,
      "learning_rate": 0.0007805007165920148,
      "loss": 1.3776,
      "step": 440000
    },
    {
      "epoch": 0.7315556530963093,
      "eval_loss": 1.3866527080535889,
      "eval_runtime": 372.9262,
      "eval_samples_per_second": 245.874,
      "eval_steps_per_second": 30.735,
      "step": 440000
    },
    {
      "epoch": 0.7648081827825052,
      "grad_norm": 0.4583888649940491,
      "learning_rate": 0.0007777005035658088,
      "loss": 1.3724,
      "step": 460000
    },
    {
      "epoch": 0.7648081827825052,
      "eval_loss": 1.3793206214904785,
      "eval_runtime": 373.9474,
      "eval_samples_per_second": 245.203,
      "eval_steps_per_second": 30.651,
      "step": 460000
    },
    {
      "epoch": 0.798060712468701,
      "grad_norm": 0.9600693583488464,
      "learning_rate": 0.0007749002905396028,
      "loss": 1.3666,
      "step": 480000
    },
    {
      "epoch": 0.798060712468701,
      "eval_loss": 1.3738141059875488,
      "eval_runtime": 374.8897,
      "eval_samples_per_second": 244.587,
      "eval_steps_per_second": 30.574,
      "step": 480000
    },
    {
      "epoch": 0.8313132421548969,
      "grad_norm": 0.31187132000923157,
      "learning_rate": 0.0007721000775133969,
      "loss": 1.3635,
      "step": 500000
    },
    {
      "epoch": 0.8313132421548969,
      "eval_loss": 1.3703372478485107,
      "eval_runtime": 369.1109,
      "eval_samples_per_second": 248.416,
      "eval_steps_per_second": 31.053,
      "step": 500000
    },
    {
      "epoch": 0.8645657718410928,
      "grad_norm": 0.5475467443466187,
      "learning_rate": 0.0007692998644871909,
      "loss": 1.3591,
      "step": 520000
    },
    {
      "epoch": 0.8645657718410928,
      "eval_loss": 1.364577293395996,
      "eval_runtime": 373.9965,
      "eval_samples_per_second": 245.171,
      "eval_steps_per_second": 30.647,
      "step": 520000
    },
    {
      "epoch": 0.8978183015272887,
      "grad_norm": 0.3919421434402466,
      "learning_rate": 0.000766499651460985,
      "loss": 1.3549,
      "step": 540000
    },
    {
      "epoch": 0.8978183015272887,
      "eval_loss": 1.3602932691574097,
      "eval_runtime": 368.621,
      "eval_samples_per_second": 248.746,
      "eval_steps_per_second": 31.094,
      "step": 540000
    },
    {
      "epoch": 0.9310708312134846,
      "grad_norm": 0.8291221857070923,
      "learning_rate": 0.000763699438434779,
      "loss": 1.3519,
      "step": 560000
    },
    {
      "epoch": 0.9310708312134846,
      "eval_loss": 1.353981852531433,
      "eval_runtime": 373.2927,
      "eval_samples_per_second": 245.633,
      "eval_steps_per_second": 30.705,
      "step": 560000
    },
    {
      "epoch": 0.9643233608996804,
      "grad_norm": 0.390234112739563,
      "learning_rate": 0.000760899225408573,
      "loss": 1.3478,
      "step": 580000
    },
    {
      "epoch": 0.9643233608996804,
      "eval_loss": 1.3524452447891235,
      "eval_runtime": 367.5147,
      "eval_samples_per_second": 249.495,
      "eval_steps_per_second": 31.188,
      "step": 580000
    },
    {
      "epoch": 0.9975758905858764,
      "grad_norm": 0.37702327966690063,
      "learning_rate": 0.0007580990123823671,
      "loss": 1.3453,
      "step": 600000
    },
    {
      "epoch": 0.9975758905858764,
      "eval_loss": 1.3504587411880493,
      "eval_runtime": 376.2908,
      "eval_samples_per_second": 243.676,
      "eval_steps_per_second": 30.46,
      "step": 600000
    },
    {
      "epoch": 1.030828420272072,
      "grad_norm": 0.6325958967208862,
      "learning_rate": 0.000755298799356161,
      "loss": 1.3368,
      "step": 620000
    },
    {
      "epoch": 1.030828420272072,
      "eval_loss": 1.344848394393921,
      "eval_runtime": 373.931,
      "eval_samples_per_second": 245.214,
      "eval_steps_per_second": 30.653,
      "step": 620000
    },
    {
      "epoch": 1.0640809499582682,
      "grad_norm": 0.5627238750457764,
      "learning_rate": 0.0007524985863299551,
      "loss": 1.3339,
      "step": 640000
    },
    {
      "epoch": 1.0640809499582682,
      "eval_loss": 1.3415149450302124,
      "eval_runtime": 379.0993,
      "eval_samples_per_second": 241.871,
      "eval_steps_per_second": 30.235,
      "step": 640000
    },
    {
      "epoch": 1.097333479644464,
      "grad_norm": 0.6864181756973267,
      "learning_rate": 0.0007496983733037491,
      "loss": 1.3315,
      "step": 660000
    },
    {
      "epoch": 1.097333479644464,
      "eval_loss": 1.3396893739700317,
      "eval_runtime": 368.6186,
      "eval_samples_per_second": 248.748,
      "eval_steps_per_second": 31.094,
      "step": 660000
    },
    {
      "epoch": 1.13058600933066,
      "grad_norm": 0.4839482307434082,
      "learning_rate": 0.0007468981602775432,
      "loss": 1.3292,
      "step": 680000
    },
    {
      "epoch": 1.13058600933066,
      "eval_loss": 1.3382230997085571,
      "eval_runtime": 375.0733,
      "eval_samples_per_second": 244.467,
      "eval_steps_per_second": 30.559,
      "step": 680000
    },
    {
      "epoch": 1.1638385390168557,
      "grad_norm": 0.5188425779342651,
      "learning_rate": 0.0007440979472513371,
      "loss": 1.3263,
      "step": 700000
    },
    {
      "epoch": 1.1638385390168557,
      "eval_loss": 1.334678292274475,
      "eval_runtime": 374.1506,
      "eval_samples_per_second": 245.07,
      "eval_steps_per_second": 30.635,
      "step": 700000
    },
    {
      "epoch": 1.1970910687030516,
      "grad_norm": 0.6367504000663757,
      "learning_rate": 0.0007412977342251311,
      "loss": 1.3242,
      "step": 720000
    },
    {
      "epoch": 1.1970910687030516,
      "eval_loss": 1.3298685550689697,
      "eval_runtime": 378.3656,
      "eval_samples_per_second": 242.34,
      "eval_steps_per_second": 30.293,
      "step": 720000
    },
    {
      "epoch": 1.2303435983892475,
      "grad_norm": 0.38538119196891785,
      "learning_rate": 0.0007384975211989252,
      "loss": 1.3219,
      "step": 740000
    },
    {
      "epoch": 1.2303435983892475,
      "eval_loss": 1.3278697729110718,
      "eval_runtime": 367.5335,
      "eval_samples_per_second": 249.482,
      "eval_steps_per_second": 31.186,
      "step": 740000
    },
    {
      "epoch": 1.2635961280754433,
      "grad_norm": 0.727473795413971,
      "learning_rate": 0.0007356973081727192,
      "loss": 1.3189,
      "step": 760000
    },
    {
      "epoch": 1.2635961280754433,
      "eval_loss": 1.3272932767868042,
      "eval_runtime": 367.1551,
      "eval_samples_per_second": 249.739,
      "eval_steps_per_second": 31.218,
      "step": 760000
    },
    {
      "epoch": 1.2968486577616392,
      "grad_norm": 0.5770161747932434,
      "learning_rate": 0.0007328970951465133,
      "loss": 1.3178,
      "step": 780000
    },
    {
      "epoch": 1.2968486577616392,
      "eval_loss": 1.3231515884399414,
      "eval_runtime": 365.4126,
      "eval_samples_per_second": 250.93,
      "eval_steps_per_second": 31.367,
      "step": 780000
    },
    {
      "epoch": 1.330101187447835,
      "grad_norm": 0.8173444271087646,
      "learning_rate": 0.0007300968821203073,
      "loss": 1.3159,
      "step": 800000
    },
    {
      "epoch": 1.330101187447835,
      "eval_loss": 1.3203078508377075,
      "eval_runtime": 365.9489,
      "eval_samples_per_second": 250.562,
      "eval_steps_per_second": 31.321,
      "step": 800000
    },
    {
      "epoch": 1.3633537171340309,
      "grad_norm": 0.7315782308578491,
      "learning_rate": 0.0007272966690941013,
      "loss": 1.3133,
      "step": 820000
    },
    {
      "epoch": 1.3633537171340309,
      "eval_loss": 1.31825590133667,
      "eval_runtime": 367.2468,
      "eval_samples_per_second": 249.677,
      "eval_steps_per_second": 31.211,
      "step": 820000
    },
    {
      "epoch": 1.3966062468202267,
      "grad_norm": 0.5089542865753174,
      "learning_rate": 0.0007244964560678954,
      "loss": 1.3109,
      "step": 840000
    },
    {
      "epoch": 1.3966062468202267,
      "eval_loss": 1.3157398700714111,
      "eval_runtime": 366.2785,
      "eval_samples_per_second": 250.337,
      "eval_steps_per_second": 31.293,
      "step": 840000
    },
    {
      "epoch": 1.4298587765064228,
      "grad_norm": 0.8854519128799438,
      "learning_rate": 0.0007216962430416894,
      "loss": 1.3103,
      "step": 860000
    },
    {
      "epoch": 1.4298587765064228,
      "eval_loss": 1.3133893013000488,
      "eval_runtime": 368.5366,
      "eval_samples_per_second": 248.803,
      "eval_steps_per_second": 31.101,
      "step": 860000
    },
    {
      "epoch": 1.4631113061926186,
      "grad_norm": 1.1718462705612183,
      "learning_rate": 0.0007188960300154835,
      "loss": 1.3081,
      "step": 880000
    },
    {
      "epoch": 1.4631113061926186,
      "eval_loss": 1.3126327991485596,
      "eval_runtime": 364.8999,
      "eval_samples_per_second": 251.283,
      "eval_steps_per_second": 31.411,
      "step": 880000
    },
    {
      "epoch": 1.4963638358788145,
      "grad_norm": 0.6334027051925659,
      "learning_rate": 0.0007160958169892775,
      "loss": 1.3069,
      "step": 900000
    },
    {
      "epoch": 1.4963638358788145,
      "eval_loss": 1.3094613552093506,
      "eval_runtime": 366.8711,
      "eval_samples_per_second": 249.932,
      "eval_steps_per_second": 31.243,
      "step": 900000
    },
    {
      "epoch": 1.5296163655650103,
      "grad_norm": 0.6082546710968018,
      "learning_rate": 0.0007132956039630715,
      "loss": 1.304,
      "step": 920000
    },
    {
      "epoch": 1.5296163655650103,
      "eval_loss": 1.3084897994995117,
      "eval_runtime": 363.9589,
      "eval_samples_per_second": 251.932,
      "eval_steps_per_second": 31.493,
      "step": 920000
    },
    {
      "epoch": 1.5628688952512062,
      "grad_norm": 0.7670090198516846,
      "learning_rate": 0.0007104953909368656,
      "loss": 1.3029,
      "step": 940000
    },
    {
      "epoch": 1.5628688952512062,
      "eval_loss": 1.305300235748291,
      "eval_runtime": 365.8471,
      "eval_samples_per_second": 250.632,
      "eval_steps_per_second": 31.33,
      "step": 940000
    },
    {
      "epoch": 1.5961214249374023,
      "grad_norm": 0.43030208349227905,
      "learning_rate": 0.0007076951779106596,
      "loss": 1.3012,
      "step": 960000
    },
    {
      "epoch": 1.5961214249374023,
      "eval_loss": 1.3027633428573608,
      "eval_runtime": 364.7767,
      "eval_samples_per_second": 251.367,
      "eval_steps_per_second": 31.422,
      "step": 960000
    },
    {
      "epoch": 1.6293739546235981,
      "grad_norm": 0.7860327363014221,
      "learning_rate": 0.0007048949648844537,
      "loss": 1.2993,
      "step": 980000
    },
    {
      "epoch": 1.6293739546235981,
      "eval_loss": 1.3039189577102661,
      "eval_runtime": 363.3226,
      "eval_samples_per_second": 252.374,
      "eval_steps_per_second": 31.548,
      "step": 980000
    },
    {
      "epoch": 1.662626484309794,
      "grad_norm": 0.3416474461555481,
      "learning_rate": 0.0007020947518582476,
      "loss": 1.2978,
      "step": 1000000
    },
    {
      "epoch": 1.662626484309794,
      "eval_loss": 1.3002079725265503,
      "eval_runtime": 375.6388,
      "eval_samples_per_second": 244.099,
      "eval_steps_per_second": 30.513,
      "step": 1000000
    },
    {
      "epoch": 1.6958790139959898,
      "grad_norm": 0.6244330406188965,
      "learning_rate": 0.0006992945388320416,
      "loss": 1.2958,
      "step": 1020000
    },
    {
      "epoch": 1.6958790139959898,
      "eval_loss": 1.2994452714920044,
      "eval_runtime": 364.5799,
      "eval_samples_per_second": 251.503,
      "eval_steps_per_second": 31.439,
      "step": 1020000
    },
    {
      "epoch": 1.7291315436821857,
      "grad_norm": 0.68141770362854,
      "learning_rate": 0.0006964943258058357,
      "loss": 1.2943,
      "step": 1040000
    },
    {
      "epoch": 1.7291315436821857,
      "eval_loss": 1.298479437828064,
      "eval_runtime": 367.378,
      "eval_samples_per_second": 249.588,
      "eval_steps_per_second": 31.199,
      "step": 1040000
    },
    {
      "epoch": 1.7623840733683815,
      "grad_norm": 0.568045437335968,
      "learning_rate": 0.0006936941127796297,
      "loss": 1.2923,
      "step": 1060000
    },
    {
      "epoch": 1.7623840733683815,
      "eval_loss": 1.2960172891616821,
      "eval_runtime": 370.477,
      "eval_samples_per_second": 247.5,
      "eval_steps_per_second": 30.938,
      "step": 1060000
    },
    {
      "epoch": 1.7956366030545774,
      "grad_norm": 0.48371127247810364,
      "learning_rate": 0.0006908938997534238,
      "loss": 1.2909,
      "step": 1080000
    },
    {
      "epoch": 1.7956366030545774,
      "eval_loss": 1.295440912246704,
      "eval_runtime": 369.8538,
      "eval_samples_per_second": 247.917,
      "eval_steps_per_second": 30.991,
      "step": 1080000
    },
    {
      "epoch": 1.8288891327407732,
      "grad_norm": 0.5598332285881042,
      "learning_rate": 0.0006880936867272178,
      "loss": 1.2906,
      "step": 1100000
    },
    {
      "epoch": 1.8288891327407732,
      "eval_loss": 1.2925302982330322,
      "eval_runtime": 369.5688,
      "eval_samples_per_second": 248.108,
      "eval_steps_per_second": 31.015,
      "step": 1100000
    },
    {
      "epoch": 1.862141662426969,
      "grad_norm": 0.6262339353561401,
      "learning_rate": 0.0006852934737010118,
      "loss": 1.289,
      "step": 1120000
    },
    {
      "epoch": 1.862141662426969,
      "eval_loss": 1.2920161485671997,
      "eval_runtime": 369.1591,
      "eval_samples_per_second": 248.383,
      "eval_steps_per_second": 31.049,
      "step": 1120000
    },
    {
      "epoch": 1.895394192113165,
      "grad_norm": 0.5510032176971436,
      "learning_rate": 0.0006824932606748059,
      "loss": 1.2877,
      "step": 1140000
    },
    {
      "epoch": 1.895394192113165,
      "eval_loss": 1.2896754741668701,
      "eval_runtime": 366.2133,
      "eval_samples_per_second": 250.381,
      "eval_steps_per_second": 31.299,
      "step": 1140000
    },
    {
      "epoch": 1.9286467217993608,
      "grad_norm": 0.7591486573219299,
      "learning_rate": 0.0006796930476485999,
      "loss": 1.2871,
      "step": 1160000
    },
    {
      "epoch": 1.9286467217993608,
      "eval_loss": 1.287521481513977,
      "eval_runtime": 364.7246,
      "eval_samples_per_second": 251.403,
      "eval_steps_per_second": 31.426,
      "step": 1160000
    },
    {
      "epoch": 1.9618992514855567,
      "grad_norm": 0.7101291418075562,
      "learning_rate": 0.000676892834622394,
      "loss": 1.2852,
      "step": 1180000
    },
    {
      "epoch": 1.9618992514855567,
      "eval_loss": 1.2871967554092407,
      "eval_runtime": 366.5323,
      "eval_samples_per_second": 250.164,
      "eval_steps_per_second": 31.271,
      "step": 1180000
    },
    {
      "epoch": 1.9951517811717525,
      "grad_norm": 1.0590598583221436,
      "learning_rate": 0.000674092621596188,
      "loss": 1.2848,
      "step": 1200000
    },
    {
      "epoch": 1.9951517811717525,
      "eval_loss": 1.2860699892044067,
      "eval_runtime": 368.8179,
      "eval_samples_per_second": 248.613,
      "eval_steps_per_second": 31.078,
      "step": 1200000
    },
    {
      "epoch": 2.0284043108579484,
      "grad_norm": 0.9100026488304138,
      "learning_rate": 0.000671292408569982,
      "loss": 1.2787,
      "step": 1220000
    },
    {
      "epoch": 2.0284043108579484,
      "eval_loss": 1.2857327461242676,
      "eval_runtime": 365.4125,
      "eval_samples_per_second": 250.93,
      "eval_steps_per_second": 31.367,
      "step": 1220000
    },
    {
      "epoch": 2.061656840544144,
      "grad_norm": 0.3401157855987549,
      "learning_rate": 0.0006684921955437761,
      "loss": 1.2775,
      "step": 1240000
    },
    {
      "epoch": 2.061656840544144,
      "eval_loss": 1.2831950187683105,
      "eval_runtime": 365.7925,
      "eval_samples_per_second": 250.669,
      "eval_steps_per_second": 31.335,
      "step": 1240000
    },
    {
      "epoch": 2.09490937023034,
      "grad_norm": 0.8612471222877502,
      "learning_rate": 0.0006656919825175701,
      "loss": 1.2756,
      "step": 1260000
    },
    {
      "epoch": 2.09490937023034,
      "eval_loss": 1.2841395139694214,
      "eval_runtime": 368.7695,
      "eval_samples_per_second": 248.646,
      "eval_steps_per_second": 31.082,
      "step": 1260000
    },
    {
      "epoch": 2.1281618999165364,
      "grad_norm": 0.6263992786407471,
      "learning_rate": 0.0006628917694913642,
      "loss": 1.2757,
      "step": 1280000
    },
    {
      "epoch": 2.1281618999165364,
      "eval_loss": 1.2808798551559448,
      "eval_runtime": 370.4864,
      "eval_samples_per_second": 247.494,
      "eval_steps_per_second": 30.938,
      "step": 1280000
    },
    {
      "epoch": 2.1614144296027322,
      "grad_norm": 0.7444067001342773,
      "learning_rate": 0.0006600915564651582,
      "loss": 1.2764,
      "step": 1300000
    },
    {
      "epoch": 2.1614144296027322,
      "eval_loss": 1.282103180885315,
      "eval_runtime": 367.703,
      "eval_samples_per_second": 249.367,
      "eval_steps_per_second": 31.172,
      "step": 1300000
    },
    {
      "epoch": 2.194666959288928,
      "grad_norm": 0.8249974250793457,
      "learning_rate": 0.0006572913434389521,
      "loss": 1.2739,
      "step": 1320000
    },
    {
      "epoch": 2.194666959288928,
      "eval_loss": 1.2793947458267212,
      "eval_runtime": 367.1309,
      "eval_samples_per_second": 249.756,
      "eval_steps_per_second": 31.22,
      "step": 1320000
    },
    {
      "epoch": 2.227919488975124,
      "grad_norm": 0.6534016132354736,
      "learning_rate": 0.0006544911304127462,
      "loss": 1.2748,
      "step": 1340000
    },
    {
      "epoch": 2.227919488975124,
      "eval_loss": 1.2775185108184814,
      "eval_runtime": 370.6914,
      "eval_samples_per_second": 247.357,
      "eval_steps_per_second": 30.921,
      "step": 1340000
    },
    {
      "epoch": 2.26117201866132,
      "grad_norm": 0.5639477968215942,
      "learning_rate": 0.0006516909173865402,
      "loss": 1.2734,
      "step": 1360000
    },
    {
      "epoch": 2.26117201866132,
      "eval_loss": 1.2764381170272827,
      "eval_runtime": 364.951,
      "eval_samples_per_second": 251.247,
      "eval_steps_per_second": 31.407,
      "step": 1360000
    },
    {
      "epoch": 2.2944245483475156,
      "grad_norm": 0.8641442656517029,
      "learning_rate": 0.0006488907043603343,
      "loss": 1.2726,
      "step": 1380000
    },
    {
      "epoch": 2.2944245483475156,
      "eval_loss": 1.277490258216858,
      "eval_runtime": 369.0258,
      "eval_samples_per_second": 248.473,
      "eval_steps_per_second": 31.06,
      "step": 1380000
    },
    {
      "epoch": 2.3276770780337115,
      "grad_norm": 0.40587782859802246,
      "learning_rate": 0.0006460904913341283,
      "loss": 1.272,
      "step": 1400000
    },
    {
      "epoch": 2.3276770780337115,
      "eval_loss": 1.2763680219650269,
      "eval_runtime": 368.7393,
      "eval_samples_per_second": 248.666,
      "eval_steps_per_second": 31.084,
      "step": 1400000
    },
    {
      "epoch": 2.3609296077199073,
      "grad_norm": 0.9067100882530212,
      "learning_rate": 0.0006432902783079223,
      "loss": 1.2706,
      "step": 1420000
    },
    {
      "epoch": 2.3609296077199073,
      "eval_loss": 1.2739602327346802,
      "eval_runtime": 368.4869,
      "eval_samples_per_second": 248.837,
      "eval_steps_per_second": 31.106,
      "step": 1420000
    },
    {
      "epoch": 2.394182137406103,
      "grad_norm": 0.553950846195221,
      "learning_rate": 0.0006404900652817164,
      "loss": 1.2646,
      "step": 1440000
    },
    {
      "epoch": 2.394182137406103,
      "eval_loss": 1.2734946012496948,
      "eval_runtime": 374.4574,
      "eval_samples_per_second": 244.869,
      "eval_steps_per_second": 30.61,
      "step": 1440000
    },
    {
      "epoch": 2.427434667092299,
      "grad_norm": 0.8403686881065369,
      "learning_rate": 0.0006376898522555104,
      "loss": 1.2658,
      "step": 1460000
    },
    {
      "epoch": 2.427434667092299,
      "eval_loss": 1.2721894979476929,
      "eval_runtime": 378.8463,
      "eval_samples_per_second": 242.032,
      "eval_steps_per_second": 30.255,
      "step": 1460000
    },
    {
      "epoch": 2.460687196778495,
      "grad_norm": 0.6338596940040588,
      "learning_rate": 0.0006348896392293044,
      "loss": 1.2653,
      "step": 1480000
    },
    {
      "epoch": 2.460687196778495,
      "eval_loss": 1.2715059518814087,
      "eval_runtime": 376.6412,
      "eval_samples_per_second": 243.449,
      "eval_steps_per_second": 30.432,
      "step": 1480000
    },
    {
      "epoch": 2.4939397264646908,
      "grad_norm": 0.47883760929107666,
      "learning_rate": 0.0006320894262030984,
      "loss": 1.265,
      "step": 1500000
    },
    {
      "epoch": 2.4939397264646908,
      "eval_loss": 1.2701904773712158,
      "eval_runtime": 368.5539,
      "eval_samples_per_second": 248.791,
      "eval_steps_per_second": 31.1,
      "step": 1500000
    },
    {
      "epoch": 2.5271922561508866,
      "grad_norm": 0.9841480255126953,
      "learning_rate": 0.0006292892131768924,
      "loss": 1.2627,
      "step": 1520000
    },
    {
      "epoch": 2.5271922561508866,
      "eval_loss": 1.2685794830322266,
      "eval_runtime": 369.2652,
      "eval_samples_per_second": 248.312,
      "eval_steps_per_second": 31.04,
      "step": 1520000
    },
    {
      "epoch": 2.5604447858370825,
      "grad_norm": 1.0926634073257446,
      "learning_rate": 0.0006264890001506865,
      "loss": 1.2634,
      "step": 1540000
    },
    {
      "epoch": 2.5604447858370825,
      "eval_loss": 1.2684801816940308,
      "eval_runtime": 366.7631,
      "eval_samples_per_second": 250.006,
      "eval_steps_per_second": 31.252,
      "step": 1540000
    },
    {
      "epoch": 2.5936973155232783,
      "grad_norm": 0.6324562430381775,
      "learning_rate": 0.0006236887871244805,
      "loss": 1.2622,
      "step": 1560000
    },
    {
      "epoch": 2.5936973155232783,
      "eval_loss": 1.2670949697494507,
      "eval_runtime": 366.4184,
      "eval_samples_per_second": 250.241,
      "eval_steps_per_second": 31.281,
      "step": 1560000
    },
    {
      "epoch": 2.626949845209474,
      "grad_norm": 1.0987452268600464,
      "learning_rate": 0.0006208885740982746,
      "loss": 1.2613,
      "step": 1580000
    },
    {
      "epoch": 2.626949845209474,
      "eval_loss": 1.267492651939392,
      "eval_runtime": 367.5623,
      "eval_samples_per_second": 249.462,
      "eval_steps_per_second": 31.184,
      "step": 1580000
    },
    {
      "epoch": 2.66020237489567,
      "grad_norm": 0.6598092913627625,
      "learning_rate": 0.0006180883610720685,
      "loss": 1.2613,
      "step": 1600000
    },
    {
      "epoch": 2.66020237489567,
      "eval_loss": 1.2656930685043335,
      "eval_runtime": 373.5303,
      "eval_samples_per_second": 245.477,
      "eval_steps_per_second": 30.686,
      "step": 1600000
    },
    {
      "epoch": 2.6934549045818663,
      "grad_norm": 0.9308195114135742,
      "learning_rate": 0.0006152881480458625,
      "loss": 1.2587,
      "step": 1620000
    },
    {
      "epoch": 2.6934549045818663,
      "eval_loss": 1.2660212516784668,
      "eval_runtime": 367.1719,
      "eval_samples_per_second": 249.728,
      "eval_steps_per_second": 31.217,
      "step": 1620000
    },
    {
      "epoch": 2.7267074342680617,
      "grad_norm": 0.9100669622421265,
      "learning_rate": 0.0006124879350196566,
      "loss": 1.2588,
      "step": 1640000
    },
    {
      "epoch": 2.7267074342680617,
      "eval_loss": 1.2644729614257812,
      "eval_runtime": 370.1389,
      "eval_samples_per_second": 247.726,
      "eval_steps_per_second": 30.967,
      "step": 1640000
    },
    {
      "epoch": 2.759959963954258,
      "grad_norm": 0.8139851093292236,
      "learning_rate": 0.0006096877219934506,
      "loss": 1.258,
      "step": 1660000
    },
    {
      "epoch": 2.759959963954258,
      "eval_loss": 1.264111876487732,
      "eval_runtime": 366.4073,
      "eval_samples_per_second": 250.249,
      "eval_steps_per_second": 31.282,
      "step": 1660000
    },
    {
      "epoch": 2.7932124936404534,
      "grad_norm": 0.7437193989753723,
      "learning_rate": 0.0006068875089672447,
      "loss": 1.2569,
      "step": 1680000
    },
    {
      "epoch": 2.7932124936404534,
      "eval_loss": 1.2626147270202637,
      "eval_runtime": 367.9517,
      "eval_samples_per_second": 249.198,
      "eval_steps_per_second": 31.151,
      "step": 1680000
    },
    {
      "epoch": 2.8264650233266497,
      "grad_norm": 0.9492677450180054,
      "learning_rate": 0.0006040872959410387,
      "loss": 1.257,
      "step": 1700000
    },
    {
      "epoch": 2.8264650233266497,
      "eval_loss": 1.2628719806671143,
      "eval_runtime": 371.0431,
      "eval_samples_per_second": 247.122,
      "eval_steps_per_second": 30.891,
      "step": 1700000
    },
    {
      "epoch": 2.8597175530128456,
      "grad_norm": 0.637161374092102,
      "learning_rate": 0.0006012870829148327,
      "loss": 1.2563,
      "step": 1720000
    },
    {
      "epoch": 2.8597175530128456,
      "eval_loss": 1.2618838548660278,
      "eval_runtime": 359.5937,
      "eval_samples_per_second": 254.991,
      "eval_steps_per_second": 31.875,
      "step": 1720000
    },
    {
      "epoch": 2.8929700826990414,
      "grad_norm": 0.6987672448158264,
      "learning_rate": 0.0005984868698886268,
      "loss": 1.2559,
      "step": 1740000
    },
    {
      "epoch": 2.8929700826990414,
      "eval_loss": 1.259372591972351,
      "eval_runtime": 367.8976,
      "eval_samples_per_second": 249.235,
      "eval_steps_per_second": 31.155,
      "step": 1740000
    },
    {
      "epoch": 2.9262226123852373,
      "grad_norm": 1.0334813594818115,
      "learning_rate": 0.0005956866568624208,
      "loss": 1.2556,
      "step": 1760000
    },
    {
      "epoch": 2.9262226123852373,
      "eval_loss": 1.2593525648117065,
      "eval_runtime": 371.5714,
      "eval_samples_per_second": 246.771,
      "eval_steps_per_second": 30.847,
      "step": 1760000
    },
    {
      "epoch": 2.959475142071433,
      "grad_norm": 1.0034544467926025,
      "learning_rate": 0.0005928864438362149,
      "loss": 1.2539,
      "step": 1780000
    },
    {
      "epoch": 2.959475142071433,
      "eval_loss": 1.2590808868408203,
      "eval_runtime": 368.5429,
      "eval_samples_per_second": 248.799,
      "eval_steps_per_second": 31.101,
      "step": 1780000
    },
    {
      "epoch": 2.992727671757629,
      "grad_norm": 1.153062343597412,
      "learning_rate": 0.0005900862308100089,
      "loss": 1.2545,
      "step": 1800000
    },
    {
      "epoch": 2.992727671757629,
      "eval_loss": 1.257894515991211,
      "eval_runtime": 374.4631,
      "eval_samples_per_second": 244.865,
      "eval_steps_per_second": 30.609,
      "step": 1800000
    },
    {
      "epoch": 3.025980201443825,
      "grad_norm": 0.857772946357727,
      "learning_rate": 0.0005872860177838029,
      "loss": 1.2513,
      "step": 1820000
    },
    {
      "epoch": 3.025980201443825,
      "eval_loss": 1.2575150728225708,
      "eval_runtime": 373.5548,
      "eval_samples_per_second": 245.461,
      "eval_steps_per_second": 30.684,
      "step": 1820000
    },
    {
      "epoch": 3.0592327311300207,
      "grad_norm": 0.5395380854606628,
      "learning_rate": 0.000584485804757597,
      "loss": 1.2491,
      "step": 1840000
    },
    {
      "epoch": 3.0592327311300207,
      "eval_loss": 1.2578082084655762,
      "eval_runtime": 372.3596,
      "eval_samples_per_second": 246.249,
      "eval_steps_per_second": 30.782,
      "step": 1840000
    },
    {
      "epoch": 3.0924852608162166,
      "grad_norm": 1.1587927341461182,
      "learning_rate": 0.000581685591731391,
      "loss": 1.2494,
      "step": 1860000
    },
    {
      "epoch": 3.0924852608162166,
      "eval_loss": 1.2557743787765503,
      "eval_runtime": 370.5248,
      "eval_samples_per_second": 247.468,
      "eval_steps_per_second": 30.935,
      "step": 1860000
    },
    {
      "epoch": 3.1257377905024124,
      "grad_norm": 0.8652488589286804,
      "learning_rate": 0.0005788853787051851,
      "loss": 1.2489,
      "step": 1880000
    },
    {
      "epoch": 3.1257377905024124,
      "eval_loss": 1.2549439668655396,
      "eval_runtime": 373.1694,
      "eval_samples_per_second": 245.714,
      "eval_steps_per_second": 30.715,
      "step": 1880000
    },
    {
      "epoch": 3.1589903201886083,
      "grad_norm": 0.8573655486106873,
      "learning_rate": 0.000576085165678979,
      "loss": 1.2497,
      "step": 1900000
    },
    {
      "epoch": 3.1589903201886083,
      "eval_loss": 1.2545205354690552,
      "eval_runtime": 369.7343,
      "eval_samples_per_second": 247.997,
      "eval_steps_per_second": 31.001,
      "step": 1900000
    },
    {
      "epoch": 3.192242849874804,
      "grad_norm": 0.5063239336013794,
      "learning_rate": 0.000573284952652773,
      "loss": 1.249,
      "step": 1920000
    },
    {
      "epoch": 3.192242849874804,
      "eval_loss": 1.253911018371582,
      "eval_runtime": 369.1217,
      "eval_samples_per_second": 248.409,
      "eval_steps_per_second": 31.052,
      "step": 1920000
    },
    {
      "epoch": 3.225495379561,
      "grad_norm": 0.8815435171127319,
      "learning_rate": 0.0005704847396265671,
      "loss": 1.2487,
      "step": 1940000
    },
    {
      "epoch": 3.225495379561,
      "eval_loss": 1.253865361213684,
      "eval_runtime": 372.8778,
      "eval_samples_per_second": 245.906,
      "eval_steps_per_second": 30.739,
      "step": 1940000
    },
    {
      "epoch": 3.258747909247196,
      "grad_norm": 0.7125207781791687,
      "learning_rate": 0.0005676845266003611,
      "loss": 1.248,
      "step": 1960000
    },
    {
      "epoch": 3.258747909247196,
      "eval_loss": 1.252898097038269,
      "eval_runtime": 370.5892,
      "eval_samples_per_second": 247.425,
      "eval_steps_per_second": 30.929,
      "step": 1960000
    },
    {
      "epoch": 3.2920004389333917,
      "grad_norm": 1.0859867334365845,
      "learning_rate": 0.0005648843135741552,
      "loss": 1.2491,
      "step": 1980000
    },
    {
      "epoch": 3.2920004389333917,
      "eval_loss": 1.25186026096344,
      "eval_runtime": 374.1998,
      "eval_samples_per_second": 245.038,
      "eval_steps_per_second": 30.631,
      "step": 1980000
    }
  ],
  "logging_steps": 20000,
  "max_steps": 6014580,
  "num_input_tokens_seen": 0,
  "num_train_epochs": 10,
  "save_steps": 20000,
  "stateful_callbacks": {
    "TrainerControl": {
      "args": {
        "should_epoch_stop": false,
        "should_evaluate": false,
        "should_log": false,
        "should_save": true,
        "should_training_stop": false
      },
      "attributes": {}
    }
  },
  "total_flos": 0.0,
  "train_batch_size": 32,
  "trial_name": null,
  "trial_params": null
}
